[
  {
    "studentName": "جمال",
    "submissionDate": "2025-11-19T15:10:58.513Z",
    "mcqScore": {
      "correct": 0,
      "total": 0
    },
    "answers": [
      {
        "type": "mcq",
        "question": "الوجود في <span style=\"color: rgb(205, 29, 29); text-decoration-line: underline;\">الفلسفة </span>يُدرس باعتباره:",
        "answer": null
      },
      {
        "type": "mcq",
        "question": "ينتمي سؤال: \"هل الوجود مادي أم روحي؟\" إلى:",
        "answer": null
      },
      {
        "type": "mcq",
        "question": "يرى أفلاطون أن عالم المثل يمثل:",
        "answer": null
      },
      {
        "type": "mcq",
        "question": "ما هو علم الأنطولوجيا؟",
        "answer": null
      },
      {
        "type": "mcq",
        "question": "من خصائص \"واجب الوجود\":",
        "answer": null
      },
      {
        "type": "mcq",
        "question": "المذهب العقلي يرى أن مصدر المعرفة هو:",
        "answer": null
      },
      {
        "type": "mcq",
        "question": "العلم الذي يدرس وسائل المعرفة وحدودها يسمى:",
        "answer": null
      },
      {
        "type": "mcq",
        "question": "القيم المطلقة تتميز بأنها:",
        "answer": null
      },
      {
        "type": "mcq",
        "question": "قيمة الخير تدرسها فلسفة:",
        "answer": null
      },
      {
        "type": "mcq",
        "question": "من فروع القيم ما يلي:",
        "answer": null
      },
      {
        "type": "mcq",
        "question": "مبحث الوجود يبحث في أصل الكون",
        "answer": null
      },
      {
        "type": "mcq",
        "question": "المعرفة الإنسانية محدودة وقاصرة بشكل مطلق",
        "answer": null
      },
      {
        "type": "mcq",
        "question": "الحدس يصنف كأحد مصادر المعرفة",
        "answer": null
      }
    ]
  },
  {
    "studentName": "فوزي",
    "submissionDate": "2025-11-19T16:09:42.370Z",
    "mcqScore": {
      "correct": 0,
      "total": 13
    },
    "tabSwitchCount": 0,
    "examTitle": "امتحان نهاية الفصل الدراسي",
    "answers": [
      {
        "question": "الوجود في <span style=\"color: rgb(205, 29, 29); text-decoration-line: underline;\">الفلسفة </span>يُدرس باعتباره:",
        "answer": "أمور أخلاقية.",
        "isCorrect": false,
        "correctAnswer": "كل ما هو كائن."
      },
      {
        "question": "ينتمي سؤال: \"هل الوجود مادي أم روحي؟\" إلى:",
        "answer": "مبحث القيم.",
        "isCorrect": false,
        "correctAnswer": "مبحث الوجود."
      },
      {
        "question": "يرى أفلاطون أن عالم المثل يمثل:",
        "answer": "القيم الأخلاقية.",
        "isCorrect": false,
        "correctAnswer": "الوجود الحقيقي."
      },
      {
        "question": "ما هو علم الأنطولوجيا؟",
        "answer": "علم النفس.",
        "isCorrect": false,
        "correctAnswer": "علم الوجود."
      },
      {
        "question": "من خصائص \"واجب الوجود\":",
        "answer": "لم تتم الإجابة",
        "isCorrect": false,
        "correctAnswer": "لا يحتاج إلى علة."
      },
      {
        "question": "المذهب العقلي يرى أن مصدر المعرفة هو:",
        "answer": "لم تتم الإجابة",
        "isCorrect": false,
        "correctAnswer": "العقل."
      },
      {
        "question": "العلم الذي يدرس وسائل المعرفة وحدودها يسمى:",
        "answer": "لم تتم الإجابة",
        "isCorrect": false,
        "correctAnswer": "الإبستمولوجيا ."
      },
      {
        "question": "القيم المطلقة تتميز بأنها:",
        "answer": "لم تتم الإجابة",
        "isCorrect": false,
        "correctAnswer": "ثابتة لا تتغير."
      },
      {
        "question": "قيمة الخير تدرسها فلسفة:",
        "answer": "لم تتم الإجابة",
        "isCorrect": false,
        "correctAnswer": "الأخلاق."
      },
      {
        "question": "من فروع القيم ما يلي:",
        "answer": "لم تتم الإجابة",
        "isCorrect": false,
        "correctAnswer": "الحق والجمال والخير."
      },
      {
        "question": "مبحث الوجود يبحث في أصل الكون",
        "answer": "لم تتم الإجابة",
        "isCorrect": false,
        "correctAnswer": "صحيح"
      },
      {
        "question": "المعرفة الإنسانية محدودة وقاصرة بشكل مطلق",
        "answer": "لم تتم الإجابة",
        "isCorrect": false,
        "correctAnswer": "خطأ"
      },
      {
        "question": "الحدس يصنف كأحد مصادر المعرفة",
        "answer": "لم تتم الإجابة",
        "isCorrect": false,
        "correctAnswer": "صحيح"
      }
    ]
  },
  {
    "studentName": "فوزي",
    "submissionDate": "2025-11-19T16:13:32.642Z",
    "mcqScore": {
      "correct": 0,
      "total": 13
    },
    "tabSwitchCount": 0,
    "examTitle": "امتحان نهاية الفصل الدراسي",
    "answers": [
      {
        "type": "mcq",
        "question": "الوجود في <span style=\"color: rgb(205, 29, 29); text-decoration-line: underline;\">الفلسفة </span>يُدرس باعتباره:",
        "answer": "لم تتم الإجابة",
        "isCorrect": false,
        "correctAnswer": "كل ما هو كائن."
      },
      {
        "type": "mcq",
        "question": "ينتمي سؤال: \"هل الوجود مادي أم روحي؟\" إلى:",
        "answer": "لم تتم الإجابة",
        "isCorrect": false,
        "correctAnswer": "مبحث الوجود."
      },
      {
        "type": "mcq",
        "question": "يرى أفلاطون أن عالم المثل يمثل:",
        "answer": "لم تتم الإجابة",
        "isCorrect": false,
        "correctAnswer": "الوجود الحقيقي."
      },
      {
        "type": "mcq",
        "question": "ما هو علم الأنطولوجيا؟",
        "answer": "لم تتم الإجابة",
        "isCorrect": false,
        "correctAnswer": "علم الوجود."
      },
      {
        "type": "mcq",
        "question": "من خصائص \"واجب الوجود\":",
        "answer": "لم تتم الإجابة",
        "isCorrect": false,
        "correctAnswer": "لا يحتاج إلى علة."
      },
      {
        "type": "mcq",
        "question": "المذهب العقلي يرى أن مصدر المعرفة هو:",
        "answer": "لم تتم الإجابة",
        "isCorrect": false,
        "correctAnswer": "العقل."
      },
      {
        "type": "mcq",
        "question": "العلم الذي يدرس وسائل المعرفة وحدودها يسمى:",
        "answer": "لم تتم الإجابة",
        "isCorrect": false,
        "correctAnswer": "الإبستمولوجيا ."
      },
      {
        "type": "mcq",
        "question": "القيم المطلقة تتميز بأنها:",
        "answer": "لم تتم الإجابة",
        "isCorrect": false,
        "correctAnswer": "ثابتة لا تتغير."
      },
      {
        "type": "mcq",
        "question": "قيمة الخير تدرسها فلسفة:",
        "answer": "لم تتم الإجابة",
        "isCorrect": false,
        "correctAnswer": "الأخلاق."
      },
      {
        "type": "mcq",
        "question": "من فروع القيم ما يلي:",
        "answer": "لم تتم الإجابة",
        "isCorrect": false,
        "correctAnswer": "الحق والجمال والخير."
      },
      {
        "type": "mcq",
        "question": "مبحث الوجود يبحث في أصل الكون",
        "answer": "لم تتم الإجابة",
        "isCorrect": false,
        "correctAnswer": "صحيح"
      },
      {
        "type": "mcq",
        "question": "المعرفة الإنسانية محدودة وقاصرة بشكل مطلق",
        "answer": "لم تتم الإجابة",
        "isCorrect": false,
        "correctAnswer": "خطأ"
      },
      {
        "type": "mcq",
        "question": "الحدس يصنف كأحد مصادر المعرفة",
        "answer": "لم تتم الإجابة",
        "isCorrect": false,
        "correctAnswer": "صحيح"
      }
    ]
  },
  {
    "studentName": "جمال",
    "submissionDate": "2025-11-19T16:43:16.038Z",
    "mcqScore": {
      "correct": 1,
      "total": 13
    },
    "tabSwitchCount": 0,
    "examTitle": "امتحان نهاية الفصل الدراسي",
    "answers": [
      {
        "type": "mcq",
        "question": "الوجود في <span style=\"color: rgb(205, 29, 29); text-decoration-line: underline;\">الفلسفة </span>يُدرس باعتباره:",
        "answer": "أمور أخلاقية.",
        "isCorrect": false,
        "correctAnswer": "كل ما هو كائن."
      },
      {
        "type": "mcq",
        "question": "ينتمي سؤال: \"هل الوجود مادي أم روحي؟\" إلى:",
        "answer": "مبحث المعرفة.",
        "isCorrect": false,
        "correctAnswer": "مبحث الوجود."
      },
      {
        "type": "mcq",
        "question": "يرى أفلاطون أن عالم المثل يمثل:",
        "answer": "المعرفة الحسية.",
        "isCorrect": false,
        "correctAnswer": "الوجود الحقيقي."
      },
      {
        "type": "mcq",
        "question": "ما هو علم الأنطولوجيا؟",
        "answer": "علم السلوك.",
        "isCorrect": false,
        "correctAnswer": "علم الوجود."
      },
      {
        "type": "mcq",
        "question": "من خصائص \"واجب الوجود\":",
        "answer": "لا يحتاج إلى علة.",
        "isCorrect": true,
        "correctAnswer": null
      },
      {
        "type": "mcq",
        "question": "المذهب العقلي يرى أن مصدر المعرفة هو:",
        "answer": "لم تتم الإجابة",
        "isCorrect": false,
        "correctAnswer": "العقل."
      },
      {
        "type": "mcq",
        "question": "العلم الذي يدرس وسائل المعرفة وحدودها يسمى:",
        "answer": "لم تتم الإجابة",
        "isCorrect": false,
        "correctAnswer": "الإبستمولوجيا ."
      },
      {
        "type": "mcq",
        "question": "القيم المطلقة تتميز بأنها:",
        "answer": "لم تتم الإجابة",
        "isCorrect": false,
        "correctAnswer": "ثابتة لا تتغير."
      },
      {
        "type": "mcq",
        "question": "قيمة الخير تدرسها فلسفة:",
        "answer": "لم تتم الإجابة",
        "isCorrect": false,
        "correctAnswer": "الأخلاق."
      },
      {
        "type": "mcq",
        "question": "من فروع القيم ما يلي:",
        "answer": "لم تتم الإجابة",
        "isCorrect": false,
        "correctAnswer": "الحق والجمال والخير."
      },
      {
        "type": "mcq",
        "question": "مبحث الوجود يبحث في أصل الكون",
        "answer": "لم تتم الإجابة",
        "isCorrect": false,
        "correctAnswer": "صحيح"
      },
      {
        "type": "mcq",
        "question": "المعرفة الإنسانية محدودة وقاصرة بشكل مطلق",
        "answer": "لم تتم الإجابة",
        "isCorrect": false,
        "correctAnswer": "خطأ"
      },
      {
        "type": "mcq",
        "question": "الحدس يصنف كأحد مصادر المعرفة",
        "answer": "لم تتم الإجابة",
        "isCorrect": false,
        "correctAnswer": "صحيح"
      }
    ]
  },
  {
    "studentName": "جمال",
    "submissionDate": "2025-11-19T16:47:59.460Z",
    "mcqScore": {
      "correct": 1,
      "total": 13
    },
    "tabSwitchCount": 0,
    "examTitle": "امتحان نهاية الفصل الدراسي",
    "answers": [
      {
        "type": "mcq",
        "question": "الوجود في <span style=\"color: rgb(205, 29, 29); text-decoration-line: underline;\">الفلسفة </span>يُدرس باعتباره:",
        "answer": "كل ما هو كائن.",
        "isCorrect": true,
        "correctAnswer": null
      },
      {
        "type": "mcq",
        "question": "ينتمي سؤال: \"هل الوجود مادي أم روحي؟\" إلى:",
        "answer": "لم تتم الإجابة",
        "isCorrect": false,
        "correctAnswer": "مبحث الوجود."
      },
      {
        "type": "mcq",
        "question": "يرى أفلاطون أن عالم المثل يمثل:",
        "answer": "لم تتم الإجابة",
        "isCorrect": false,
        "correctAnswer": "الوجود الحقيقي."
      },
      {
        "type": "mcq",
        "question": "ما هو علم الأنطولوجيا؟",
        "answer": "لم تتم الإجابة",
        "isCorrect": false,
        "correctAnswer": "علم الوجود."
      },
      {
        "type": "mcq",
        "question": "من خصائص \"واجب الوجود\":",
        "answer": "لم تتم الإجابة",
        "isCorrect": false,
        "correctAnswer": "لا يحتاج إلى علة."
      },
      {
        "type": "mcq",
        "question": "المذهب العقلي يرى أن مصدر المعرفة هو:",
        "answer": "لم تتم الإجابة",
        "isCorrect": false,
        "correctAnswer": "العقل."
      },
      {
        "type": "mcq",
        "question": "العلم الذي يدرس وسائل المعرفة وحدودها يسمى:",
        "answer": "لم تتم الإجابة",
        "isCorrect": false,
        "correctAnswer": "الإبستمولوجيا ."
      },
      {
        "type": "mcq",
        "question": "القيم المطلقة تتميز بأنها:",
        "answer": "لم تتم الإجابة",
        "isCorrect": false,
        "correctAnswer": "ثابتة لا تتغير."
      },
      {
        "type": "mcq",
        "question": "قيمة الخير تدرسها فلسفة:",
        "answer": "لم تتم الإجابة",
        "isCorrect": false,
        "correctAnswer": "الأخلاق."
      },
      {
        "type": "mcq",
        "question": "من فروع القيم ما يلي:",
        "answer": "لم تتم الإجابة",
        "isCorrect": false,
        "correctAnswer": "الحق والجمال والخير."
      },
      {
        "type": "mcq",
        "question": "مبحث الوجود يبحث في أصل الكون",
        "answer": "لم تتم الإجابة",
        "isCorrect": false,
        "correctAnswer": "صحيح"
      },
      {
        "type": "mcq",
        "question": "المعرفة الإنسانية محدودة وقاصرة بشكل مطلق",
        "answer": "لم تتم الإجابة",
        "isCorrect": false,
        "correctAnswer": "خطأ"
      },
      {
        "type": "mcq",
        "question": "الحدس يصنف كأحد مصادر المعرفة",
        "answer": "لم تتم الإجابة",
        "isCorrect": false,
        "correctAnswer": "صحيح"
      }
    ]
  },
  {
    "studentName": "احمد",
    "submissionDate": "2025-11-19T18:16:45.805Z",
    "mcqScore": {
      "correct": 4,
      "total": 15
    },
    "tabSwitchCount": 0,
    "examTitle": "امتحان نهاية الفصل الدراسي",
    "answers": [
      {
        "type": "essay",
        "question": "ما هي أهمية دراسة تاريخ وفلسفة القانون بالنسبة لـدارس القانون تحديداً؟",
        "answer": null,
        "isGraded": false,
        "maxScore": 0
      },
      {
        "type": "mcq",
        "question": "ما هي المرحلة الأولى من مراحل نشأة القانون الأربع وفقاً للرؤية الوضعية؟",
        "answer": "مرحلة التقاليد العرفية.",
        "isCorrect": false,
        "correctAnswer": "مرحلة القوة أو الانتقام الفردي."
      },
      {
        "type": "mcq",
        "question": "ما هي الشرائع التي تسود العالم اليوم، والتي تمثل العلاقة بين الأصل والفرع بالنسبة للقانون؟",
        "answer": "القانون الروماني، القانون اليهودي، القانون الفرعوني.",
        "isCorrect": false,
        "correctAnswer": "الشريعة الإسلامية، الشريعة اللاتينية، الشريعة الأنجلوسكسونية."
      },
      {
        "type": "mcq",
        "question": "يُعد قانون 'أور نمو' الأقدم بين المدونات القانونية المكتشفة، وهو سابق لقانون حمورابي بثلاثة قرون تقريباً.",
        "answer": "خطأ",
        "isCorrect": false,
        "correctAnswer": "صحيح"
      },
      {
        "type": "mcq",
        "question": " يقوم التشريع الإسلامي على مصدرين أساسيين هما القرآن الكريم والسنة النبوية، بالإضافة إلى مصادر أخرى فرعية مثل الإجماع والقياس.",
        "answer": "صحيح",
        "isCorrect": true,
        "correctAnswer": null
      },
      {
        "type": "mcq",
        "question": "ما هي الوسيلة الفعالة التي تمكّن المجتمع من تحقيق الاستقرار مع ضمان التقدم؟",
        "answer": "القوة.",
        "isCorrect": false,
        "correctAnswer": "القانون."
      },
      {
        "type": "mcq",
        "question": "وفقاً للمذهب الوضعي (اللاعقلي) في العلاقة بين القانون والأخلاق، ما هو موقفه؟",
        "answer": "وجوب الفصل بين القانون والأخلاق.",
        "isCorrect": true,
        "correctAnswer": null
      },
      {
        "type": "mcq",
        "question": "في مرحلة القوة أو الانتقام الفردي، كانت الملكية العقارية معروفة وسائدة منذ البداية.",
        "answer": "خطأ",
        "isCorrect": true,
        "correctAnswer": null
      },
      {
        "type": "mcq",
        "question": "وفقاً للرؤية الدينية (القرآنية) لنشأة القانون، ما هي المرحلة التي تبدأ بنبي الله إبراهيم عليه السلام وتتميز بقيادة الأنبياء لحركة التوحيد قيادة ميدانية؟",
        "answer": " مرحلة الكمال.",
        "isCorrect": false,
        "correctAnswer": "مرحلة الإمامة (الدولة)."
      },
      {
        "type": "mcq",
        "question": "ما هي الخاصية التي تضمن أن القاعدة القانونية تسري على جميع الأشخاص والوقائع في الظروف المماثلة؟",
        "answer": "أنها عامة ومجردة.",
        "isCorrect": true,
        "correctAnswer": null
      },
      {
        "type": "mcq",
        "question": "العلاقة بين وجود القانون ووجود الدولة هي علاقة تلازم، بحيث لا يمكن أن يوجد أحدهما دون الآخر.",
        "answer": "لم تتم الإجابة",
        "isCorrect": false,
        "correctAnswer": "خطأ"
      },
      {
        "type": "mcq",
        "question": "متى ظهرت ظاهرة الطبقية داخل المجتمعات وفقاً لمراحل نشأة القانون؟",
        "answer": "لم تتم الإجابة",
        "isCorrect": false,
        "correctAnswer": " مرحلة التقاليد العرفية."
      },
      {
        "type": "mcq",
        "question": "في مرحلة التقاليد الدينية، كيف تغيّر مركز المرأة الاجتماعي؟",
        "answer": "لم تتم الإجابة",
        "isCorrect": false,
        "correctAnswer": "قلّ مركزها وأصبحت في حكم المال المملوك لأبيها ثم لزوجها."
      },
      {
        "type": "essay",
        "question": "قارن بين الرؤية الوضعية (التطورية) والرؤية الدينية (القرآنية) لنشأة القانون من حيث تقسيم المراحل. ثم بيّن أهم الاختلافات الجوهرية بين مرحلة القوة/الانتقام الفردي (في الرؤية الوضعية) ومرحلة الفطرة (في الرؤية الدينية).",
        "answer": null,
        "isGraded": false,
        "maxScore": 0
      },
      {
        "type": "mcq",
        "question": "ما هو الهدف الأساسي من سَنّ قانون 'سوق شمَّر' في اليمن القديمة؟",
        "answer": "لم تتم الإجابة",
        "isCorrect": false,
        "correctAnswer": "ضمان حقوق الدولة في جباية الضرائب وحماية الصالح العام."
      },
      {
        "type": "mcq",
        "question": "ما هو المبدأ الذي أخذه قانون 'أور نمو' في تحديد العقوبة، بخلاف قانون حمورابي الذي اتسم بالقسوة؟",
        "answer": "لم تتم الإجابة",
        "isCorrect": false,
        "correctAnswer": "مبدأ التعويض."
      },
      {
        "type": "mcq",
        "question": "التدوين يعتبر مرحلة مستقلة ورابعة من مراحل نشأة القانون وفقاً للنص، حيث تكتمل خصائص القاعدة القانونية عند التدوين.",
        "answer": "لم تتم الإجابة",
        "isCorrect": false,
        "correctAnswer": "خطأ"
      }
    ]
  },
  {
    "studentName": "جمال",
    "submissionDate": "2025-11-20T06:59:25.016Z",
    "mcqScore": {
      "correct": 1,
      "total": 13
    },
    "tabSwitchCount": 0,
    "examTitle": "امتحان نهاية الفصل الدراسي",
    "answers": [
      {
        "question": "الوجود في <span style=\"color: rgb(205, 29, 29); text-decoration-line: underline;\">الفلسفة </span>يُدرس باعتباره:",
        "type": "mcq",
        "isCorrect": false
      },
      {
        "question": "ينتمي سؤال: \"هل الوجود مادي أم روحي؟\" إلى:",
        "type": "mcq",
        "isCorrect": false
      },
      {
        "question": "يرى أفلاطون أن عالم المثل يمثل:",
        "type": "mcq",
        "isCorrect": false
      },
      {
        "question": "ما هو علم الأنطولوجيا؟",
        "type": "mcq",
        "isCorrect": false
      },
      {
        "question": "من خصائص \"واجب الوجود\":",
        "type": "mcq",
        "isCorrect": false
      },
      {
        "question": "المذهب العقلي يرى أن مصدر المعرفة هو:",
        "type": "mcq",
        "isCorrect": false
      },
      {
        "question": "العلم الذي يدرس وسائل المعرفة وحدودها يسمى:",
        "type": "mcq",
        "isCorrect": false
      },
      {
        "question": "القيم المطلقة تتميز بأنها:",
        "type": "mcq",
        "isCorrect": false
      },
      {
        "question": "قيمة الخير تدرسها فلسفة:",
        "type": "mcq",
        "isCorrect": false
      },
      {
        "question": "من فروع القيم ما يلي:",
        "type": "mcq",
        "isCorrect": false
      },
      {
        "question": "مبحث الوجود يبحث في أصل الكون",
        "type": "mcq",
        "isCorrect": false
      },
      {
        "question": "المعرفة الإنسانية محدودة وقاصرة بشكل مطلق",
        "type": "mcq",
        "answer": "صحيح",
        "isCorrect": false
      },
      {
        "question": "الحدس يصنف كأحد مصادر المعرفة",
        "type": "mcq",
        "answer": "صحيح",
        "isCorrect": true
      }
    ]
  },
  {
    "studentName": "جمال",
    "submissionDate": "2025-11-20T07:00:52.104Z",
    "mcqScore": {
      "correct": 6,
      "total": 13
    },
    "tabSwitchCount": 0,
    "examTitle": "امتحان نهاية الفصل الدراسي",
    "answers": [
      {
        "type": "mcq",
        "question": "الوجود في <span style=\"color: rgb(205, 29, 29); text-decoration-line: underline;\">الفلسفة </span>يُدرس باعتباره:",
        "answer": "كل ما هو كائن.",
        "isCorrect": true,
        "correctAnswer": null
      },
      {
        "type": "mcq",
        "question": "ينتمي سؤال: \"هل الوجود مادي أم روحي؟\" إلى:",
        "answer": "مبحث القيم.",
        "isCorrect": false,
        "correctAnswer": "مبحث الوجود."
      },
      {
        "type": "mcq",
        "question": "يرى أفلاطون أن عالم المثل يمثل:",
        "answer": "المعرفة الحسية.",
        "isCorrect": false,
        "correctAnswer": "الوجود الحقيقي."
      },
      {
        "type": "mcq",
        "question": "ما هو علم الأنطولوجيا؟",
        "answer": "علم الوجود.",
        "isCorrect": true,
        "correctAnswer": null
      },
      {
        "type": "mcq",
        "question": "من خصائص \"واجب الوجود\":",
        "answer": "لم تتم الإجابة",
        "isCorrect": false,
        "correctAnswer": "لا يحتاج إلى علة."
      },
      {
        "type": "mcq",
        "question": "المذهب العقلي يرى أن مصدر المعرفة هو:",
        "answer": "العقل.",
        "isCorrect": true,
        "correctAnswer": null
      },
      {
        "type": "mcq",
        "question": "العلم الذي يدرس وسائل المعرفة وحدودها يسمى:",
        "answer": "اللوجيكا.",
        "isCorrect": false,
        "correctAnswer": "الإبستمولوجيا ."
      },
      {
        "type": "mcq",
        "question": "القيم المطلقة تتميز بأنها:",
        "answer": "لم تتم الإجابة",
        "isCorrect": false,
        "correctAnswer": "ثابتة لا تتغير."
      },
      {
        "type": "mcq",
        "question": "قيمة الخير تدرسها فلسفة:",
        "answer": "الأخلاق.",
        "isCorrect": true,
        "correctAnswer": null
      },
      {
        "type": "mcq",
        "question": "من فروع القيم ما يلي:",
        "answer": "الوجود والمعرفة.",
        "isCorrect": false,
        "correctAnswer": "الحق والجمال والخير."
      },
      {
        "type": "mcq",
        "question": "مبحث الوجود يبحث في أصل الكون",
        "answer": "صحيح",
        "isCorrect": true,
        "correctAnswer": null
      },
      {
        "type": "mcq",
        "question": "المعرفة الإنسانية محدودة وقاصرة بشكل مطلق",
        "answer": "صحيح",
        "isCorrect": false,
        "correctAnswer": "خطأ"
      },
      {
        "type": "mcq",
        "question": "الحدس يصنف كأحد مصادر المعرفة",
        "answer": "صحيح",
        "isCorrect": true,
        "correctAnswer": null
      }
    ]
  },
  {
    "studentName": "جمال",
    "submissionDate": "2025-11-20T08:03:09.736Z",
    "mcqScore": {
      "correct": 2,
      "total": 13
    },
    "tabSwitchCount": 0,
    "examTitle": "امتحان نهاية الفصل الدراسي",
    "answers": [
      {
        "type": "mcq",
        "question": "ما هو علم الأنطولوجيا؟",
        "answer": "علم اللغة.",
        "isCorrect": false,
        "correctAnswer": "علم الوجود."
      },
      {
        "type": "mcq",
        "question": "من فروع القيم ما يلي:",
        "answer": "الحق والجمال والخير.",
        "isCorrect": true,
        "correctAnswer": null
      },
      {
        "type": "mcq",
        "question": "يرى أفلاطون أن عالم المثل يمثل:",
        "answer": "المعرفة الحسية.",
        "isCorrect": false,
        "correctAnswer": "الوجود الحقيقي."
      },
      {
        "type": "mcq",
        "question": "الحدس يصنف كأحد مصادر المعرفة",
        "answer": "صحيح",
        "isCorrect": true,
        "correctAnswer": null
      },
      {
        "type": "mcq",
        "question": "المعرفة الإنسانية محدودة وقاصرة بشكل مطلق",
        "answer": "لم تتم الإجابة",
        "isCorrect": false,
        "correctAnswer": "خطأ"
      },
      {
        "type": "mcq",
        "question": "العلم الذي يدرس وسائل المعرفة وحدودها يسمى:",
        "answer": "لم تتم الإجابة",
        "isCorrect": false,
        "correctAnswer": "الإبستمولوجيا ."
      },
      {
        "type": "mcq",
        "question": "ينتمي سؤال: \"هل الوجود مادي أم روحي؟\" إلى:",
        "answer": "لم تتم الإجابة",
        "isCorrect": false,
        "correctAnswer": "مبحث الوجود."
      },
      {
        "type": "mcq",
        "question": "القيم المطلقة تتميز بأنها:",
        "answer": "لم تتم الإجابة",
        "isCorrect": false,
        "correctAnswer": "ثابتة لا تتغير."
      },
      {
        "type": "mcq",
        "question": "من خصائص \"واجب الوجود\":",
        "answer": "لم تتم الإجابة",
        "isCorrect": false,
        "correctAnswer": "لا يحتاج إلى علة."
      },
      {
        "type": "mcq",
        "question": "المذهب العقلي يرى أن مصدر المعرفة هو:",
        "answer": "لم تتم الإجابة",
        "isCorrect": false,
        "correctAnswer": "العقل."
      },
      {
        "type": "mcq",
        "question": "الوجود في <span style=\"color: rgb(205, 29, 29); text-decoration-line: underline;\">الفلسفة </span>يُدرس باعتباره:",
        "answer": "لم تتم الإجابة",
        "isCorrect": false,
        "correctAnswer": "كل ما هو كائن."
      },
      {
        "type": "mcq",
        "question": "مبحث الوجود يبحث في أصل الكون",
        "answer": "لم تتم الإجابة",
        "isCorrect": false,
        "correctAnswer": "صحيح"
      },
      {
        "type": "mcq",
        "question": "قيمة الخير تدرسها فلسفة:",
        "answer": "لم تتم الإجابة",
        "isCorrect": false,
        "correctAnswer": "الأخلاق."
      }
    ]
  },
  {
    "studentName": "جمال",
    "submissionDate": "2025-11-20T08:27:10.248Z",
    "mcqScore": {
      "correct": 2,
      "total": 13
    },
    "tabSwitchCount": 0,
    "examTitle": "امتحان نهاية الفصل الدراسي",
    "answers": [
      {
        "type": "mcq",
        "question": "يرى أفلاطون أن عالم المثل يمثل:",
        "answer": "الوجود الحقيقي.",
        "isCorrect": true,
        "correctAnswer": null
      },
      {
        "type": "mcq",
        "question": "ما هو علم الأنطولوجيا؟",
        "answer": "علم النفس.",
        "isCorrect": false,
        "correctAnswer": "علم الوجود."
      },
      {
        "type": "mcq",
        "question": "المعرفة الإنسانية محدودة وقاصرة بشكل مطلق",
        "answer": "خطأ",
        "isCorrect": true,
        "correctAnswer": null
      },
      {
        "type": "mcq",
        "question": "العلم الذي يدرس وسائل المعرفة وحدودها يسمى:",
        "answer": "لم تتم الإجابة",
        "isCorrect": false,
        "correctAnswer": "الإبستمولوجيا ."
      },
      {
        "type": "mcq",
        "question": "المذهب العقلي يرى أن مصدر المعرفة هو:",
        "answer": "لم تتم الإجابة",
        "isCorrect": false,
        "correctAnswer": "العقل."
      },
      {
        "type": "mcq",
        "question": "قيمة الخير تدرسها فلسفة:",
        "answer": "لم تتم الإجابة",
        "isCorrect": false,
        "correctAnswer": "الأخلاق."
      },
      {
        "type": "mcq",
        "question": "من خصائص \"واجب الوجود\":",
        "answer": "لم تتم الإجابة",
        "isCorrect": false,
        "correctAnswer": "لا يحتاج إلى علة."
      },
      {
        "type": "mcq",
        "question": "ينتمي سؤال: \"هل الوجود مادي أم روحي؟\" إلى:",
        "answer": "لم تتم الإجابة",
        "isCorrect": false,
        "correctAnswer": "مبحث الوجود."
      },
      {
        "type": "mcq",
        "question": "من فروع القيم ما يلي:",
        "answer": "لم تتم الإجابة",
        "isCorrect": false,
        "correctAnswer": "الحق والجمال والخير."
      },
      {
        "type": "mcq",
        "question": "الحدس يصنف كأحد مصادر المعرفة",
        "answer": "لم تتم الإجابة",
        "isCorrect": false,
        "correctAnswer": "صحيح"
      },
      {
        "type": "mcq",
        "question": "مبحث الوجود يبحث في أصل الكون",
        "answer": "لم تتم الإجابة",
        "isCorrect": false,
        "correctAnswer": "صحيح"
      },
      {
        "type": "mcq",
        "question": "الوجود في <span style=\"color: rgb(205, 29, 29); text-decoration-line: underline;\">الفلسفة </span>يُدرس باعتباره:",
        "answer": "ظواهر حسية فقط.",
        "isCorrect": false,
        "correctAnswer": "كل ما هو كائن."
      },
      {
        "type": "mcq",
        "question": "القيم المطلقة تتميز بأنها:",
        "answer": "لم تتم الإجابة",
        "isCorrect": false,
        "correctAnswer": "ثابتة لا تتغير."
      }
    ]
  },
  {
    "studentName": "فوزي",
    "submissionDate": "2025-11-20T08:56:05.237Z",
    "mcqScore": {
      "correct": 0,
      "total": 13
    },
    "tabSwitchCount": 0,
    "examTitle": "امتحان نهاية الفصل الدراسي",
    "answers": [
      {
        "type": "mcq",
        "question": "الوجود في <span style=\"color: rgb(205, 29, 29); text-decoration-line: underline;\">الفلسفة </span>يُدرس باعتباره:",
        "answer": "لم تتم الإجابة",
        "isCorrect": false,
        "correctAnswer": "كل ما هو كائن."
      },
      {
        "type": "mcq",
        "question": "المعرفة الإنسانية محدودة وقاصرة بشكل مطلق",
        "answer": "لم تتم الإجابة",
        "isCorrect": false,
        "correctAnswer": "خطأ"
      },
      {
        "type": "mcq",
        "question": "ما هو علم الأنطولوجيا؟",
        "answer": "لم تتم الإجابة",
        "isCorrect": false,
        "correctAnswer": "علم الوجود."
      },
      {
        "type": "mcq",
        "question": "من خصائص \"واجب الوجود\":",
        "answer": "لم تتم الإجابة",
        "isCorrect": false,
        "correctAnswer": "لا يحتاج إلى علة."
      },
      {
        "type": "mcq",
        "question": "ينتمي سؤال: \"هل الوجود مادي أم روحي؟\" إلى:",
        "answer": "لم تتم الإجابة",
        "isCorrect": false,
        "correctAnswer": "مبحث الوجود."
      },
      {
        "type": "mcq",
        "question": "يرى أفلاطون أن عالم المثل يمثل:",
        "answer": "لم تتم الإجابة",
        "isCorrect": false,
        "correctAnswer": "الوجود الحقيقي."
      },
      {
        "type": "mcq",
        "question": "القيم المطلقة تتميز بأنها:",
        "answer": "لم تتم الإجابة",
        "isCorrect": false,
        "correctAnswer": "ثابتة لا تتغير."
      },
      {
        "type": "mcq",
        "question": "الحدس يصنف كأحد مصادر المعرفة",
        "answer": "لم تتم الإجابة",
        "isCorrect": false,
        "correctAnswer": "صحيح"
      },
      {
        "type": "mcq",
        "question": "من فروع القيم ما يلي:",
        "answer": "لم تتم الإجابة",
        "isCorrect": false,
        "correctAnswer": "الحق والجمال والخير."
      },
      {
        "type": "mcq",
        "question": "قيمة الخير تدرسها فلسفة:",
        "answer": "لم تتم الإجابة",
        "isCorrect": false,
        "correctAnswer": "الأخلاق."
      },
      {
        "type": "mcq",
        "question": "العلم الذي يدرس وسائل المعرفة وحدودها يسمى:",
        "answer": "لم تتم الإجابة",
        "isCorrect": false,
        "correctAnswer": "الإبستمولوجيا ."
      },
      {
        "type": "mcq",
        "question": "المذهب العقلي يرى أن مصدر المعرفة هو:",
        "answer": "لم تتم الإجابة",
        "isCorrect": false,
        "correctAnswer": "العقل."
      },
      {
        "type": "mcq",
        "question": "مبحث الوجود يبحث في أصل الكون",
        "answer": "لم تتم الإجابة",
        "isCorrect": false,
        "correctAnswer": "صحيح"
      }
    ]
  }
]